{
  "payload_meta": {
    "doc_id": 15730112,
    "document_ref": "M-860325-30387",
    "xml_len": 3780,
    "process_url": "https://pipedrive-worker-ixilvz5ewa-ew.a.run.app/process"
  },
  "payload_sent_to_worker_keys": [
    "id",
    "client",
    "deal",
    "meta",
    "paytraq_full_xml"
  ],
  "worker_response": {
    "status": "created",
    "deal_id": 67100,
    "title": "PT 15730112 M-860325-30387",
    "_trace": [
      {
        "step": "01_deal_upsert",
        "ok": true
      },
      {
        "step": "02_parse_line_items",
        "ok": true
      },
      {
        "step": "03_products_sync",
        "ok": true
      },
      {
        "step": "04_find_update_organization",
        "ok": true
      },
      {
        "step": "05_find_update_person",
        "ok": true
      },
      {
        "step": "99_update_products",
        "ok": true
      }
    ],
    "document_id": 15730112,
    "step_02_fetch": {
      "used_fallback_fetch": false
    },
    "step_02": {
      "ok": true
    },
    "line_items_count": 2,
    "line_items_preview": [
      {
        "name": "easyCARE nitrile flex Nitrila cimdi, N100, S izmērs, [RNBKS10003]",
        "code": "RNBKS10003",
        "quantity": 10.0,
        "unit_price": 3.3,
        "gross_unit_price": 3.99,
        "include_tax": true,
        "vat_rate": 0.21,
        "tax_key_name": "PVN 21%",
        "line_discount_pct": 0.0,
        "price_source": "paytraq_price_field"
      },
      {
        "name": "Shipping [Ship1]",
        "code": "Ship1",
        "quantity": 1.0,
        "unit_price": 1.81,
        "gross_unit_price": 2.19,
        "include_tax": true,
        "vat_rate": 0.21,
        "tax_key_name": "PVN 21%",
        "line_discount_pct": 0.0,
        "price_source": "shipping_charge"
      }
    ],
    "step_03": {
      "ok": true,
      "attached_count": 2
    },
    "products_attached": [
      {
        "product_id": 7417,
        "name": "easyCARE nitrile flex Nitrila cimdi, N100, S izmērs, [RNBKS10003]",
        "quantity": 10.0,
        "src_unit_price_net": 3.3,
        "src_gross_unit_price": 3.99,
        "src_include_tax": true,
        "src_vat_rate": 0.21,
        "pipedrive_item_price": 3.99,
        "pipedrive_tax_method": "inclusive",
        "pipedrive_tax": 21,
        "added_id": 2445
      },
      {
        "product_id": 7418,
        "name": "Shipping [Ship1]",
        "quantity": 1.0,
        "src_unit_price_net": 1.81,
        "src_gross_unit_price": 2.19,
        "src_include_tax": true,
        "src_vat_rate": 0.21,
        "pipedrive_item_price": 2.19,
        "pipedrive_tax_method": "inclusive",
        "pipedrive_tax": 21,
        "added_id": 2446
      }
    ],
    "products_created": [
      {
        "name": "easyCARE nitrile flex Nitrila cimdi, N100, S izmērs, [RNBKS10003]",
        "id": 7417,
        "reason": "not_found"
      },
      {
        "name": "Shipping [Ship1]",
        "id": 7418,
        "reason": "not_found"
      }
    ],
    "activities_created": [],
    "step_04": {
      "ok": true,
      "mode": "paytraq_direct",
      "client_id": 1204154,
      "found_by": "email",
      "org_action": "updated",
      "org_id": 14015,
      "attached_to_deal": true,
      "paytraq_fields": {
        "name": "Ieva Socka",
        "email": "ievasocka@gmail.com",
        "phone": "25123594",
        "regnr": null,
        "vatnr": null,
        "country": "LV",
        "legal_address_formatted": "Nameja 1, Jekabpils, Lv-5201, LV"
      },
      "pipedrive_search": {
        "attempts": [
          {
            "by": "regnr",
            "term": null,
            "skipped": true
          },
          {
            "by": "email",
            "term": "ievasocka@gmail.com",
            "found": true
          }
        ]
      },
      "pipedrive_update_fields": {
        "email": {
          "key": "faac2c792221bf18216ef17eae1941feef9a17cc",
          "value": "ievasocka@gmail.com"
        },
        "phone": {
          "key": "4b4db855bb2ac128d585e2d84c554eb099e588f7",
          "value": "25123594"
        },
        "country": {
          "key": "0905a8eedcb78f85063132a4aa37b76c0fc7da1d",
          "value": "LV"
        },
        "address": {
          "key": "address",
          "value": "Nameja 1, Jekabpils, Lv-5201, LV"
        },
        "shipping_address": {
          "key": "dae3df0edeadce95ba223719cc18141795387de8",
          "value": "Nameja 1, Jekabpils, Lv-5201, LV"
        }
      },
      "note": null,
      "dup_check": {
        "potential_duplicates": true,
        "activity_created": true,
        "activity_id": 22977,
        "skipped_reason": null,
        "debug": {
          "by": {
            "regnr": {
              "term": null,
              "skipped": true,
              "candidates": []
            },
            "email": {
              "term": "ievasocka@gmail.com",
              "candidates": [
                {
                  "id": 14015,
                  "name": "Ieva Socka"
                }
              ]
            },
            "phone": {
              "term": "25123594",
              "candidates": []
            },
            "name": {
              "term": "Ieva Socka",
              "candidates": [
                {
                  "id": 14015,
                  "name": "Ieva Socka"
                },
                {
                  "id": 13408,
                  "name": "Ieva Socka"
                }
              ]
            }
          },
          "unique_ids": [
            14015,
            13408
          ]
        }
      }
    },
    "step_05": {
      "ok": true,
      "mode": "person_attach_v1_no_activity",
      "deal_id": 67100,
      "org_id": 14015,
      "found_by": "email",
      "person_id": 15098,
      "attached_to_deal": true,
      "activity_created": false,
      "activity_id": null,
      "pipedrive_search": {
        "attempts": [
          {
            "by": "email",
            "term": "ievasocka@gmail.com",
            "found": true
          }
        ]
      },
      "note": "Person matched by email. Activity disabled."
    },
    "step_99": {
      "ok": true,
      "mode": "pubsub_publish",
      "topic": "projects/jaunais-za-aizv04022026/topics/org-update-queue",
      "payload": {
        "deal_id": 67100,
        "document_id": 15730112,
        "client_id": 1204154
      },
      "message_id": "18028356677325762"
    }
  }
}