{
  "payload_meta": {
    "doc_id": 16764804,
    "document_ref": "PAS/0726/00010",
    "xml_len": 2227,
    "process_url": "https://pipedrive-worker-ixilvz5ewa-ew.a.run.app/process"
  },
  "payload_sent_to_worker_keys": [
    "id",
    "client",
    "deal",
    "meta",
    "paytraq_full_xml"
  ],
  "worker_response": {
    "status": "updated",
    "deal_id": 70430,
    "title": "PAS/0726/00010",
    "_trace": [
      {
        "step": "01_deal_upsert",
        "ok": true
      },
      {
        "step": "02_parse_line_items",
        "ok": true
      },
      {
        "step": "03_products_sync",
        "ok": true
      },
      {
        "step": "04_find_update_organization",
        "ok": true
      },
      {
        "step": "05_find_update_person",
        "ok": true
      },
      {
        "step": "97_write_invoice_to_db",
        "ok": true
      },
      {
        "step": "98_save_mozello_map",
        "ok": true
      },
      {
        "step": "99_update_products",
        "ok": true
      }
    ],
    "document_id": 16764804,
    "step_02_fetch": {
      "used_fallback_fetch": false
    },
    "step_02": {
      "ok": true
    },
    "line_items_count": 0,
    "line_items_preview": [],
    "step_03": {
      "skipped": true,
      "reason": "No line_items"
    },
    "products_attached": null,
    "products_created": null,
    "activities_created": null,
    "step_04": {
      "ok": true,
      "version": "v2026-03-12-step04-db-first-01",
      "mode": "paytraq_direct_db_first",
      "client_id": 617942,
      "found_by": "phone",
      "org_action": "skipped_no_changes",
      "org_id": 14066,
      "attached_to_deal": true,
      "paytraq_fields": {
        "name": "RAIVIS PARAUGI",
        "email": "info@tiktik.lv",
        "phone": "26711822",
        "regnr": null,
        "vatnr": null,
        "country": "LV",
        "legal_address_formatted": "Atmodas iela 86-41, Jelgava, 3007, LV"
      },
      "db_search": {
        "attempts": [
          {
            "by": "regnr",
            "term": null,
            "skipped": true
          },
          {
            "by": "email",
            "term": "info@tiktik.lv",
            "found": false,
            "candidate_count": 0
          },
          {
            "by": "phone",
            "term": "26711822",
            "found": true,
            "candidate_count": 2
          }
        ]
      },
      "pipedrive_search": {},
      "pipedrive_update_fields": {},
      "note": null,
      "update_filter_debug": {
        "kept_keys": [],
        "skipped_same_keys": [
          "faac2c792221bf18216ef17eae1941feef9a17cc",
          "4b4db855bb2ac128d585e2d84c554eb099e588f7",
          "0905a8eedcb78f85063132a4aa37b76c0fc7da1d",
          "address",
          "dae3df0edeadce95ba223719cc18141795387de8"
        ],
        "skipped_same": {
          "faac2c792221bf18216ef17eae1941feef9a17cc": {
            "new": "info@tiktik.lv",
            "old": "info@tiktik.lv",
            "reason": "same"
          },
          "4b4db855bb2ac128d585e2d84c554eb099e588f7": {
            "new": "26711822",
            "old": "26711822",
            "reason": "same"
          },
          "0905a8eedcb78f85063132a4aa37b76c0fc7da1d": {
            "new": "LV",
            "old": "LV",
            "reason": "same"
          },
          "address": {
            "new": "Atmodas iela 86-41, Jelgava, 3007, LV",
            "old": "Atmodas iela 86-41, Jelgava, 3007, LV",
            "reason": "same"
          },
          "dae3df0edeadce95ba223719cc18141795387de8": {
            "new": "Atmodas iela 86-41, Jelgava, 3007, LV",
            "old": "Atmodas iela 86-41, Jelgava, 3007, LV",
            "reason": "same"
          }
        }
      },
      "dup_check": {
        "potential_duplicates": false,
        "activity_created": false,
        "activity_id": null,
        "skipped_reason": "db_match_no_pipedrive_dup_scan"
      }
    },
    "step_05": {
      "ok": true,
      "version": "v2026-03-10-step05-reuse-deal-person-01",
      "mode": "person_attach_v1_no_activity",
      "deal_id": 70430,
      "org_id": 14066,
      "found_by": "email",
      "person_id": 10714,
      "attached_to_deal": true,
      "activity_created": false,
      "activity_id": null,
      "pipedrive_search": {
        "attempts": [
          {
            "by": "email",
            "term": "info@tiktik.lv",
            "found": true
          }
        ]
      },
      "note": "Person matched by email. Activity disabled.",
      "person_country_field_key": "a1a8f673391eacef699614e5fd4c74a5e4c014de",
      "person_country_value": "LV",
      "person_country_previous": "LV",
      "person_country_updated": false,
      "person_country_checked": true
    },
    "step_97": {
      "ok": true,
      "invoice_no": "PAS/0726/00010",
      "invoice_rows": 1,
      "line_rows": 0,
      "invoice_errors": [],
      "line_errors": [],
      "dataset": "paytraq_sync"
    },
    "step_98": {
      "ok": true,
      "saved": false,
      "skipped": true,
      "reason": "doc_ref_not_mozello",
      "doc_ref": "PAS/0726/00010"
    },
    "step_99": {
      "ok": true,
      "mode": "pubsub_publish",
      "doc_ref": "PAS/0726/00010",
      "org_update": {
        "topic": "projects/jaunais-za-aizv04022026/topics/org-update-queue",
        "payload": {
          "deal_id": 70430,
          "document_id": 16764804,
          "client_id": 617942
        },
        "message_id": "20517048655154609"
      },
      "mozello_enrich": {
        "skipped": true,
        "reason": "doc_ref_not_mozello",
        "topic": "projects/jaunais-za-aizv04022026/topics/mozello-enrich-queue",
        "doc_ref": "PAS/0726/00010"
      }
    }
  }
}