{
  "payload_meta": {
    "doc_id": 15689837,
    "document_ref": "M-860325-30247",
    "xml_len": 3649,
    "process_url": "https://pipedrive-worker-142693968214.europe-west1.run.app/process"
  },
  "payload_sent_to_worker_keys": [
    "id",
    "client",
    "deal",
    "meta",
    "paytraq_full_xml"
  ],
  "worker_response": {
    "status": "updated",
    "deal_id": 66857,
    "title": "PT 15689837 M-860325-30247",
    "_trace": [
      {
        "step": "01_deal_upsert",
        "ok": true
      },
      {
        "step": "02_parse_line_items",
        "ok": true
      },
      {
        "step": "03_products_sync",
        "ok": true
      },
      {
        "step": "04_find_update_organization",
        "ok": true
      },
      {
        "step": "05_find_update_person",
        "ok": true
      },
      {
        "step": "99_update_products",
        "ok": true
      }
    ],
    "document_id": 15689837,
    "step_02_fetch": {
      "used_fallback_fetch": false
    },
    "step_02": {
      "ok": true
    },
    "line_items_count": 2,
    "line_items_preview": [
      {
        "name": "Bahilas Zilas N100 [FOL-CPE/B/22]",
        "code": "FOL-CPE/B/22",
        "quantity": 5.0,
        "unit_price": 1.81,
        "gross_unit_price": 2.19,
        "include_tax": true,
        "vat_rate": 0.21,
        "tax_key_name": "PVN 21%",
        "line_discount_pct": 0.0,
        "price_source": "paytraq_price_field"
      },
      {
        "name": "Shipping [Ship1]",
        "code": "Ship1",
        "quantity": 1.0,
        "unit_price": 2.39,
        "gross_unit_price": 2.89,
        "include_tax": true,
        "vat_rate": 0.21,
        "tax_key_name": "PVN 21%",
        "line_discount_pct": 0.0,
        "price_source": "shipping_charge"
      }
    ],
    "step_03": {
      "ok": true,
      "attached_count": 0
    },
    "products_attached": [
      {
        "product_id": 7109,
        "skipped": true,
        "reason": "already_on_deal",
        "name": "Vienreizlietojamas Bahilas 100gb zilas, 22 paciņas - 1 transporta kaste, FOL-CPE/B/22-Kast [22-Kast]"
      },
      {
        "product_id": 7107,
        "skipped": true,
        "reason": "already_on_deal",
        "name": "Shipping [Ship1]"
      }
    ],
    "products_created": [],
    "activities_created": [],
    "step_04": {
      "ok": true,
      "mode": "paytraq_direct",
      "client_id": 1198292,
      "found_by": "email",
      "org_action": "updated",
      "org_id": 13978,
      "attached_to_deal": true,
      "paytraq_fields": {
        "name": "Līva Čevere",
        "email": "liva.cevere@gmail.com",
        "phone": "25123857",
        "regnr": null,
        "vatnr": null,
        "country": "LV",
        "legal_address_formatted": "Jaunā gatve 35, Ogre, LV-5001, LV"
      },
      "pipedrive_search": {
        "attempts": [
          {
            "by": "regnr",
            "term": null,
            "skipped": true
          },
          {
            "by": "email",
            "term": "liva.cevere@gmail.com",
            "found": true
          }
        ]
      },
      "pipedrive_update_fields": {
        "email": {
          "key": "faac2c792221bf18216ef17eae1941feef9a17cc",
          "value": "liva.cevere@gmail.com"
        },
        "phone": {
          "key": "4b4db855bb2ac128d585e2d84c554eb099e588f7",
          "value": "25123857"
        },
        "country": {
          "key": "0905a8eedcb78f85063132a4aa37b76c0fc7da1d",
          "value": "LV"
        },
        "address": {
          "key": "address",
          "value": "Jaunā gatve 35, Ogre, LV-5001, LV"
        },
        "shipping_address": {
          "key": "dae3df0edeadce95ba223719cc18141795387de8",
          "value": "Jaunā gatve 35, Ogre, LV-5001, LV"
        }
      },
      "note": null
    },
    "step_05": {
      "ok": true,
      "mode": "person_attach_v1_no_activity",
      "deal_id": 66857,
      "org_id": 13978,
      "found_by": "email",
      "person_id": 15065,
      "attached_to_deal": true,
      "activity_created": false,
      "activity_id": null,
      "pipedrive_search": {
        "attempts": [
          {
            "by": "email",
            "term": "liva.cevere@gmail.com",
            "found": true
          }
        ]
      },
      "note": "Person matched by email. Activity disabled."
    },
    "step_99": {
      "ok": true,
      "mode": "pubsub_publish",
      "topic": "projects/jaunais-za-aizv04022026/topics/org-update-queue",
      "payload": {
        "deal_id": 66857,
        "document_id": 15689837
      },
      "message_id": "17982831714304474"
    }
  }
}